{
    "Pinwheels": {
        "Preparation Error": 34,
        "Measurement Error": 10,
        "Order Error": 4,
        "Timing Error": 5,
        "Technique Error": 21,
        "Temperature Error": 5,
        "Missing Step": 22,
        "Other": 1
    },
    "Tomato Mozzarella Salad": {
        "Preparation Error": 11,
        "Measurement Error": 7,
        "Order Error": 5,
        "Timing Error": 2,
        "Technique Error": 22,
        "Temperature Error": 1,
        "Missing Step": 8,
        "Other": 0
    },
    "Butter Corn Cup": {
        "Preparation Error": 8,
        "Measurement Error": 5,
        "Order Error": 5,
        "Timing Error": 6,
        "Technique Error": 24,
        "Temperature Error": 3,
        "Missing Step": 15,
        "Other": 2
    },
    "Tomato Chutney": {
        "Preparation Error": 8,
        "Measurement Error": 18,
        "Order Error": 3,
        "Timing Error": 11,
        "Technique Error": 24,
        "Temperature Error": 9,
        "Missing Step": 18,
        "Other": 0
    },
    "Scrambled Eggs": {
        "Preparation Error": 15,
        "Measurement Error": 28,
        "Order Error": 4,
        "Timing Error": 11,
        "Technique Error": 44,
        "Temperature Error": 9,
        "Missing Step": 22,
        "Other": 2
    },
    "Cucumber Raita": {
        "Preparation Error": 23,
        "Measurement Error": 12,
        "Order Error": 6,
        "Timing Error": 0,
        "Technique Error": 21,
        "Temperature Error": 0,
        "Missing Step": 11,
        "Other": 0
    },
    "Zoodles": {
        "Preparation Error": 11,
        "Measurement Error": 7,
        "Order Error": 4,
        "Timing Error": 7,
        "Technique Error": 27,
        "Temperature Error": 6,
        "Missing Step": 7,
        "Other": 2
    },
    "Microwave Egg Sandwich": {
        "Preparation Error": 21,
        "Measurement Error": 25,
        "Order Error": 7,
        "Timing Error": 17,
        "Technique Error": 20,
        "Temperature Error": 5,
        "Missing Step": 12,
        "Other": 2
    },
    "Sauted Mushrooms": {
        "Preparation Error": 19,
        "Measurement Error": 14,
        "Order Error": 5,
        "Timing Error": 13,
        "Technique Error": 29,
        "Temperature Error": 6,
        "Missing Step": 10,
        "Other": 0
    },
    "Blender Banana Pancakes": {
        "Preparation Error": 9,
        "Measurement Error": 14,
        "Order Error": 6,
        "Timing Error": 11,
        "Technique Error": 21,
        "Temperature Error": 4,
        "Missing Step": 12,
        "Other": 0
    },
    "Herb Omelet with Fried Tomatoes": {
        "Preparation Error": 12,
        "Measurement Error": 10,
        "Order Error": 7,
        "Timing Error": 6,
        "Technique Error": 27,
        "Temperature Error": 2,
        "Missing Step": 15,
        "Other": 0
    },
    "Broccoli Stir Fry": {
        "Preparation Error": 4,
        "Measurement Error": 13,
        "Order Error": 4,
        "Timing Error": 3,
        "Technique Error": 18,
        "Temperature Error": 2,
        "Missing Step": 16,
        "Other": 0
    },
    "Pan Fried Tofu": {
        "Preparation Error": 1,
        "Measurement Error": 5,
        "Order Error": 7,
        "Timing Error": 4,
        "Technique Error": 11,
        "Temperature Error": 2,
        "Missing Step": 9,
        "Other": 0
    },
    "Mug Cake": {
        "Preparation Error": 30,
        "Measurement Error": 15,
        "Order Error": 2,
        "Timing Error": 7,
        "Technique Error": 20,
        "Temperature Error": 1,
        "Missing Step": 21,
        "Other": 1
    },
    "Cheese Pimiento": {
        "Preparation Error": 8,
        "Measurement Error": 12,
        "Order Error": 4,
        "Timing Error": 7,
        "Technique Error": 15,
        "Temperature Error": 1,
        "Missing Step": 6,
        "Other": 0
    },
    "Spicy Tuna Avocado Wraps": {
        "Preparation Error": 17,
        "Measurement Error": 26,
        "Order Error": 6,
        "Timing Error": 2,
        "Technique Error": 23,
        "Temperature Error": 0,
        "Missing Step": 23,
        "Other": 0
    },
    "Caprese Bruschetta": {
        "Preparation Error": 18,
        "Measurement Error": 9,
        "Order Error": 5,
        "Timing Error": 6,
        "Technique Error": 26,
        "Temperature Error": 2,
        "Missing Step": 11,
        "Other": 0
    },
    "Dressed Up Meatballs": {
        "Preparation Error": 9,
        "Measurement Error": 28,
        "Order Error": 6,
        "Timing Error": 15,
        "Technique Error": 25,
        "Temperature Error": 3,
        "Missing Step": 16,
        "Other": 0
    },
    "Microwave Mug Pizza": {
        "Preparation Error": 13,
        "Measurement Error": 8,
        "Order Error": 5,
        "Timing Error": 3,
        "Technique Error": 6,
        "Temperature Error": 0,
        "Missing Step": 3,
        "Other": 1
    },
    "Ramen": {
        "Preparation Error": 10,
        "Measurement Error": 6,
        "Order Error": 4,
        "Timing Error": 10,
        "Technique Error": 18,
        "Temperature Error": 4,
        "Missing Step": 8,
        "Other": 0
    },
    "Coffee": {
        "Preparation Error": 12,
        "Measurement Error": 11,
        "Order Error": 2,
        "Timing Error": 10,
        "Technique Error": 20,
        "Temperature Error": 4,
        "Missing Step": 11,
        "Other": 0
    },
    "Breakfast Burritos": {
        "Preparation Error": 15,
        "Measurement Error": 12,
        "Order Error": 6,
        "Timing Error": 9,
        "Technique Error": 17,
        "Temperature Error": 0,
        "Missing Step": 7,
        "Other": 0
    },
    "Spiced Hot Chocolate": {
        "Preparation Error": 13,
        "Measurement Error": 15,
        "Order Error": 5,
        "Timing Error": 11,
        "Technique Error": 12,
        "Temperature Error": 5,
        "Missing Step": 10,
        "Other": 0
    },
    "Microwave French Toast": {
        "Preparation Error": 8,
        "Measurement Error": 7,
        "Order Error": 2,
        "Timing Error": 5,
        "Technique Error": 6,
        "Temperature Error": 4,
        "Missing Step": 3,
        "Other": 0
    }
}