{"steps": {"0": "START", "192": "Cook-Cook for 2 minutes or until the zoodles are done", "193": "Add-1/6 cup grated parmesan cheese", "194": "season-pepper to taste", "195": "Top-Top with more parmesan if desired", "196": "Heat-Heat a large pan on medium heat", "197": "Remove-Remove from heat", "198": "season-season with salt", "199": "Add-Add 1 large minced garlic cloves to the pan", "200": "Peel-Peel 1 garlic cloves", "201": "Add-Add the zucchini noodles", "202": "Cook-Cook garlic until fragrant (about 1 minutes). Be careful not to burn garlic", "203": "Spiralize-Spiralize 1 medium zucchini into thin noodles using a spiralizer", "204": "Melt-Melt 1 tablespoons of softened butter", "1000": "END"}, "edges": [[198, 192], [201, 192], [193, 192], [194, 192], [202, 193], [202, 194], [197, 195], [203, 196], [200, 196], [192, 197], [202, 198], [204, 199], [202, 201], [199, 202], [196, 204], [0, 200], [0, 203], [195, 1000]]}